[{"Item":"Item Corsair 275Q ATX Mid Tower Case","Previous":"Previous$89.99","Current":"Current$82.99","Where":"WhereNewegg","Save":"Save$7.00","Drop":"Drop8%","Promo":"Promo","Unnamed: 7":"Add"},{"Item":"Item Antec P110 Luce ATX Mid Tower Case","Previous":"Previous$104.98","Current":"Current$59.99","Where":"WhereNewegg","Save":"Save$44.99","Drop":"Drop43%","Promo":"Promo  $40.00 mail-in rebate","Unnamed: 7":"Add"},{"Item":"Item Antec NX1000 ATX Mid Tower Case","Previous":"Previous$84.99","Current":"Current$49.99","Where":"WhereNewegg","Save":"Save$35.00","Drop":"Drop42%","Promo":"Promo  $35.00 mail-in rebate","Unnamed: 7":"Add"},{"Item":"Item Corsair SPEC-05 ATX Mid Tower Case","Previous":"Previous$63.98","Current":"Current$44.99","Where":"WhereNewegg","Save":"Save$18.99","Drop":"Drop30%","Promo":"Promo  $15.00 mail-in rebate","Unnamed: 7":"Add"},{"Item":"Item Antec P101 Silent ATX Mid Tower Case","Previous":"Previous$118.16","Current":"Current$84.99","Where":"WhereNewegg","Save":"Save$33.17","Drop":"Drop29%","Promo":"Promo  $20.00 mail-in rebate","Unnamed: 7":"Add"},{"Item":"Item Corsair iCUE 465X RGB ATX Mid Tower Case","Previous":"Previous$149.00","Current":"Current$109.99","Where":"WhereNewegg","Save":"Save$39.01","Drop":"Drop27%","Promo":"Promo  $20.00 mail-in rebate","Unnamed: 7":"Add"},{"Item":"Item Phanteks P300 ATX Mid Tower Case","Previous":"Previous$67.93","Current":"Current$49.99","Where":"WhereNewegg","Save":"Save$17.94","Drop":"Drop27%","Promo":"Promo  $10.00 mail-in rebate","Unnamed: 7":"Add"},{"Item":"Item Metallic Gear Neo Air ATX Mid Tower Case","Previous":"Previous$65.98","Current":"Current$49.99","Where":"WhereNewegg","Save":"Save$15.99","Drop":"Drop25%","Promo":"Promo  $10.00 mail-in rebate","Unnamed: 7":"Add"},{"Item":"Item Thermaltake Versa H21 ATX Mid Tower Case","Previous":"Previous$57.95","Current":"Current$44.99","Where":"WhereWalmart","Save":"Save$12.96","Drop":"Drop23%","Promo":"Promo","Unnamed: 7":"Add"},{"Item":"Item Antec P110 Silent ATX Mid Tower Case","Previous":"Previous$101.98","Current":"Current$79.99","Where":"WhereNewegg","Save":"Save$21.99","Drop":"Drop22%","Promo":"Promo  $15.00 mail-in rebate","Unnamed: 7":"Add"},{"Item":"Item Phanteks Eclipse P360X ATX Mid Tower Case","Previous":"Previous$87.98","Current":"Current$69.99","Where":"WhereNewegg","Save":"Save$17.99","Drop":"Drop21%","Promo":"Promo  $10.00 mail-in rebate","Unnamed: 7":"Add"},{"Item":"Item Phanteks Eclipse P400 ATX Mid Tower Case","Previous":"Previous$86.87","Current":"Current$69.88","Where":"WhereNewegg","Save":"Save$16.99","Drop":"Drop20%","Promo":"Promo  $10.00 mail-in rebate","Unnamed: 7":"Add"},{"Item":"Item Metallic Gear Neo Micro V2 MicroATX Mid Tower Case","Previous":"Previous$91.98","Current":"Current$74.99","Where":"WhereNewegg","Save":"Save$16.99","Drop":"Drop19%","Promo":"Promo  $10.00 mail-in rebate","Unnamed: 7":"Add"},{"Item":"Item Phanteks Eclipse P400 ATX Mid Tower Case","Previous":"Previous$85.98","Current":"Current$69.99","Where":"WhereNewegg","Save":"Save$15.99","Drop":"Drop19%","Promo":"Promo  $10.00 mail-in rebate","Unnamed: 7":"Add"},{"Item":"Item Phanteks Eclipse P400S ATX Mid Tower Case","Previous":"Previous$89.99","Current":"Current$74.99","Where":"WhereNewegg","Save":"Save$15.00","Drop":"Drop17%","Promo":"Promo  $15.00 mail-in rebate","Unnamed: 7":"Add"},{"Item":"Item Thermaltake S500 ATX Mid Tower Case","Previous":"Previous$138.21","Current":"Current$116.98","Where":"WhereNewegg","Save":"Save$21.23","Drop":"Drop16%","Promo":"Promo","Unnamed: 7":"Add"},{"Item":"Item Corsair iCUE 220T RGB Airflow ATX Mid Tower Case","Previous":"Previous$105.99","Current":"Current$89.99","Where":"WhereNewegg","Save":"Save$16.00","Drop":"Drop16%","Promo":"Promo  $10.00 mail-in rebate","Unnamed: 7":"Add"},{"Item":"Item Cooler Master MasterBox K500 ATX Mid Tower Case","Previous":"Previous$87.98","Current":"Current$73.99","Where":"WhereWalmart","Save":"Save$13.99","Drop":"Drop16%","Promo":"Promo","Unnamed: 7":"Add"},{"Item":"Item Fractal Design Focus G ATX Mid Tower Case","Previous":"Previous$64.99","Current":"Current$54.99","Where":"WhereWalmart","Save":"Save$10.00","Drop":"Drop16%","Promo":"Promo","Unnamed: 7":"Add"},{"Item":"Item Fractal Design Focus G ATX Mid Tower Case","Previous":"Previous$60.97","Current":"Current$52.98","Where":"WhereWalmart","Save":"Save$7.99","Drop":"Drop14%","Promo":"Promo","Unnamed: 7":"Add"},{"Item":"Item Deepcool TESSERACT BF ATX Mid Tower Case","Previous":"Previous$57.97","Current":"Current$49.99","Where":"WhereB&H","Save":"Save$7.98","Drop":"Drop14%","Promo":"Promo","Unnamed: 7":"Add"},{"Item":"Item Corsair 500D Premium ATX Mid Tower Case","Previous":"Previous$159.97","Current":"Current$139.97","Where":"WhereNewegg","Save":"Save$20.00","Drop":"Drop13%","Promo":"Promo  $20.00 mail-in rebate","Unnamed: 7":"Add"},{"Item":"Item Corsair Crystal 570X RGB ATX Mid Tower Case","Previous":"Previous$179.99","Current":"Current$159.99","Where":"WhereNewegg","Save":"Save$20.00","Drop":"Drop12%","Promo":"Promo","Unnamed: 7":"Add"},{"Item":"Item Thermaltake Core V1 Mini ITX Desktop Case","Previous":"Previous$55.98","Current":"Current$49.73","Where":"WhereWalmart","Save":"Save$6.25","Drop":"Drop12%","Promo":"Promo","Unnamed: 7":"Add"},{"Item":"Item Corsair SPEC-06 ATX Mid Tower Case","Previous":"Previous$99.99","Current":"Current$89.99","Where":"WhereNewegg","Save":"Save$10.00","Drop":"Drop11%","Promo":"Promo","Unnamed: 7":"Add"},{"Item":"Item Deepcool Gamer Storm MACUBE 550 ATX Mid Tower Case","Previous":"Previous$99.99","Current":"Current$89.99","Where":"WhereNewegg","Save":"Save$10.00","Drop":"Drop11%","Promo":"Promo","Unnamed: 7":"Add"},{"Item":"Item Phanteks ENTHOO EVOLV SHIFT Mini ITX Tower Case","Previous":"Previous$117.98","Current":"Current$107.98","Where":"WhereNewegg","Save":"Save$10.00","Drop":"Drop9%","Promo":"Promo  $10.00 mail-in rebate","Unnamed: 7":"Add"},{"Item":"Item Cooler Master MasterBox MB511 RGB ATX Mid Tower Case","Previous":"Previous$97.98","Current":"Current$89.99","Where":"WhereB&H","Save":"Save$7.99","Drop":"Drop9%","Promo":"Promo","Unnamed: 7":"Add"},{"Item":"Item Deepcool Gamer Storm MACUBE 310 ATX Mid Tower Case","Previous":"Previous$59.99","Current":"Current$54.99","Where":"WhereNewegg","Save":"Save$5.00","Drop":"Drop9%","Promo":"Promo","Unnamed: 7":"Add"},{"Item":"Item Thermaltake Versa H18 MicroATX Mini Tower Case","Previous":"Previous$61.98","Current":"Current$56.98","Where":"WhereNewegg","Save":"Save$5.00","Drop":"Drop9%","Promo":"Promo","Unnamed: 7":"Add"},{"Item":"Item DIYPC DIY-D3-RGB ATX Mid Tower Case","Previous":"Previous$56.98","Current":"Current$51.99","Where":"WhereNewegg","Save":"Save$4.99","Drop":"Drop9%","Promo":"Promo  + 10% off w\/ promo code 36GAMDN9, limited offer","Unnamed: 7":"Add"},{"Item":"Item Thermaltake Core P3 ATX Mid Tower Case","Previous":"Previous$139.99","Current":"Current$128.99","Where":"WhereNewegg","Save":"Save$11.00","Drop":"Drop8%","Promo":"Promo","Unnamed: 7":"Add"},{"Item":"Item NZXT H700 ATX Mid Tower Case","Previous":"Previous$139.99","Current":"Current$129.99","Where":"WhereNewegg","Save":"Save$10.00","Drop":"Drop8%","Promo":"Promo","Unnamed: 7":"Add"},{"Item":"Item Phanteks Enthoo Primo ATX Full Tower Case","Previous":"Previous$250.98","Current":"Current$234.99","Where":"WhereNewegg","Save":"Save$15.99","Drop":"Drop7%","Promo":"Promo  $10.00 mail-in rebate","Unnamed: 7":"Add"},{"Item":"Item Phanteks ECLIPSE P600S ATX Mid Tower Case","Previous":"Previous$171.98","Current":"Current$160.98","Where":"WhereNewegg","Save":"Save$11.00","Drop":"Drop7%","Promo":"Promo","Unnamed: 7":"Add"},{"Item":"Item Thermaltake Commander C35 TG ARGB ATX Mid Tower Case","Previous":"Previous$118.93","Current":"Current$110.98","Where":"WhereNewegg","Save":"Save$7.95","Drop":"Drop7%","Promo":"Promo","Unnamed: 7":"Add"},{"Item":"Item Corsair 275R Airflow ATX Mid Tower Case","Previous":"Previous$85.98","Current":"Current$79.99","Where":"WhereNewegg","Save":"Save$5.99","Drop":"Drop7%","Promo":"Promo","Unnamed: 7":"Add"},{"Item":"Item Deepcool Gamer Storm MACUBE 310 ATX Mid Tower Case","Previous":"Previous$58.99","Current":"Current$54.99","Where":"WhereNewegg","Save":"Save$4.00","Drop":"Drop7%","Promo":"Promo","Unnamed: 7":"Add"},{"Item":"Item Deepcool Gamer Storm MACUBE 550 ATX Mid Tower Case","Previous":"Previous$105.99","Current":"Current$99.99","Where":"WhereNewegg","Save":"Save$6.00","Drop":"Drop6%","Promo":"Promo","Unnamed: 7":"Add"},{"Item":"Item Antec Dark Avenger DA601 ATX Mid Tower Case","Previous":"Previous$94.98","Current":"Current$89.98","Where":"WhereNewegg","Save":"Save$5.00","Drop":"Drop6%","Promo":"Promo","Unnamed: 7":"Add"},{"Item":"Item Antec NX310 ATX Mid Tower Case","Previous":"Previous$71.98","Current":"Current$67.98","Where":"WhereNewegg","Save":"Save$4.00","Drop":"Drop6%","Promo":"Promo","Unnamed: 7":"Add"},{"Item":"Item Corsair Carbide Series 275R ATX Mid Tower Case","Previous":"Previous$79.99","Current":"Current$75.99","Where":"WhereNewegg","Save":"Save$4.00","Drop":"Drop6%","Promo":"Promo","Unnamed: 7":"Add"},{"Item":"Item Antec Dark Phantom DP501 ATX Mid Tower Case","Previous":"Previous$94.41","Current":"Current$89.98","Where":"WhereNewegg","Save":"Save$4.43","Drop":"Drop5%","Promo":"Promo","Unnamed: 7":"Add"},{"Item":"Item Corsair iCUE 220T RGB Airflow ATX Mid Tower Case","Previous":"Previous$99.99","Current":"Current$95.99","Where":"WhereBest Buy","Save":"Save$4.00","Drop":"Drop5%","Promo":"Promo","Unnamed: 7":"Add"},{"Item":"Item Phanteks Enthoo Primo ATX Full Tower Case","Previous":"Previous$249.98","Current":"Current$239.99","Where":"WhereNewegg","Save":"Save$9.99","Drop":"Drop4%","Promo":"Promo  $10.00 mail-in rebate","Unnamed: 7":"Add"},{"Item":"Item Corsair iCUE 465X RGB ATX Mid Tower Case","Previous":"Previous$134.99","Current":"Current$129.99","Where":"WhereNewegg","Save":"Save$5.00","Drop":"Drop4%","Promo":"Promo","Unnamed: 7":"Add"},{"Item":"Item Fractal Design Design Define R6 USB-C Blackout ATX Mid Tower Case","Previous":"Previous$159.98","Current":"Current$154.98","Where":"WhereNewegg","Save":"Save$5.00","Drop":"Drop4%","Promo":"Promo","Unnamed: 7":"Add"},{"Item":"Item Phanteks Enthoo EVOLV TG MicroATX Mini Tower Case","Previous":"Previous$125.98","Current":"Current$121.98","Where":"WhereNewegg","Save":"Save$4.00","Drop":"Drop4%","Promo":"Promo","Unnamed: 7":"Add"},{"Item":"Item Thermaltake View 31 TG ATX Mid Tower Case","Previous":"Previous$129.99","Current":"Current$125.99","Where":"WhereNewegg","Save":"Save$4.00","Drop":"Drop4%","Promo":"Promo","Unnamed: 7":"Add"},{"Item":"Item Thermaltake Versa H17 MicroATX Mini Tower Case","Previous":"Previous$51.98","Current":"Current$49.98","Where":"WhereNewegg","Save":"Save$2.00","Drop":"Drop4%","Promo":"Promo","Unnamed: 7":"Add"},{"Item":"Item Phanteks Enthoo EVOLV TG MicroATX Mini Tower Case","Previous":"Previous$130.98","Current":"Current$127.98","Where":"WhereNewegg","Save":"Save$3.00","Drop":"Drop3%","Promo":"Promo  $10.00 mail-in rebate","Unnamed: 7":"Add"},{"Item":"Item Cougar Gemini M MicroATX Mini Tower Case","Previous":"Previous$66.98","Current":"Current$64.98","Where":"WhereNewegg","Save":"Save$2.00","Drop":"Drop3%","Promo":"Promo","Unnamed: 7":"Add"},{"Item":"Item DIYPC DIY-A1-BK ATX Mid Tower Case","Previous":"Previous$48.98","Current":"Current$47.87","Where":"WhereNewegg","Save":"Save$1.11","Drop":"Drop3%","Promo":"Promo","Unnamed: 7":"Add"},{"Item":"Item HEC HX300 ATX Mid Tower Case","Previous":"Previous$35.98","Current":"Current$34.98","Where":"WhereNewegg","Save":"Save$1.00","Drop":"Drop3%","Promo":"Promo","Unnamed: 7":"Add"},{"Item":"Item Corsair iCUE 220T RGB ATX Mid Tower Case","Previous":"Previous$105.99","Current":"Current$103.98","Where":"WhereNewegg","Save":"Save$2.01","Drop":"Drop2%","Promo":"Promo","Unnamed: 7":"Add"},{"Item":"Item Corsair iCUE 220T RGB ATX Mid Tower Case","Previous":"Previous$105.99","Current":"Current$103.98","Where":"WhereNewegg","Save":"Save$2.01","Drop":"Drop2%","Promo":"Promo","Unnamed: 7":"Add"},{"Item":"Item Fractal Design Define S2 Blackout ATX Mid Tower Case","Previous":"Previous$141.98","Current":"Current$139.98","Where":"WhereNewegg","Save":"Save$2.00","Drop":"Drop2%","Promo":"Promo","Unnamed: 7":"Add"},{"Item":"Item Cougar Turret ATX Mid Tower Case","Previous":"Previous$71.99","Current":"Current$70.98","Where":"WhereNewegg","Save":"Save$1.01","Drop":"Drop2%","Promo":"Promo","Unnamed: 7":"Add"},{"Item":"Item Cougar Gemini S ATX Mid Tower Case","Previous":"Previous$87.98","Current":"Current$86.98","Where":"WhereNewegg","Save":"Save$1.00","Drop":"Drop2%","Promo":"Promo","Unnamed: 7":"Add"}]